xia_engine_terraform_gcs/__init__.py
xia_engine_terraform_gcs/engine.cp311-win_amd64.pyd
xia_engine_terraform_gcs-0.1.5.dist-info/LICENSE.txt
xia_engine_terraform_gcs-0.1.5.dist-info/METADATA
xia_engine_terraform_gcs-0.1.5.dist-info/WHEEL
xia_engine_terraform_gcs-0.1.5.dist-info/top_level.txt
xia_engine_terraform_gcs-0.1.5.dist-info/RECORD
