Metadata-Version: 2.1
Name: xia-engine-terraform-gcs
Version: 0.1.5
Home-page: https://develop.x-i-a.com/docs/xia-engine-terraform-gcs/0.1.5/index.html
Author: X-I-A
Author-email: admin@x-i-a.com
Requires-Python: >=3.9
License-File: LICENSE.txt
Requires-Dist: jinja2
Requires-Dist: google-cloud-storage
Requires-Dist: xia-engine-terraform
